alireza/__init__.py
alireza/DjangoTools/__Error_Handler.py
alireza/DjangoTools/__init__.py
alireza/DjangoTools/__manager.py
alireza/UsefulTools/__Error_Handler.py
alireza/UsefulTools/__init__.py
alireza/UsefulTools/__manager.py
alireza-0.0.5.dist-info/METADATA
alireza-0.0.5.dist-info/WHEEL
alireza-0.0.5.dist-info/top_level.txt
alireza-0.0.5.dist-info/RECORD
