Metadata-Version: 2.1
Name: alireza
Version: 0.0.5
Summary: Comprehensive Toolkit for Boosting Productivity in Python Frameworks Development
Home-page: UNKNOWN
Author: Alireza Soroush
Author-email: alirezasoroush@hotmail.com
License: UNKNOWN
Keywords: python,tools,framework,django
Platform: UNKNOWN
Classifier: Development Status :: 1 - Planning
Classifier: Intended Audience :: Developers
Classifier: Programming Language :: Python :: 3
Classifier: Operating System :: Unix
Classifier: Operating System :: MacOS :: MacOS X
Classifier: Operating System :: Microsoft :: Windows
Requires-Python: >=3.6
